calculator/__init__.py
calculator/calculator.py
calculator_halimah-0.0.2.dist-info/LICENSE
calculator_halimah-0.0.2.dist-info/METADATA
calculator_halimah-0.0.2.dist-info/WHEEL
calculator_halimah-0.0.2.dist-info/top_level.txt
calculator_halimah-0.0.2.dist-info/RECORD
