Metadata-Version: 2.1
Name: calculator-halimah
Version: 0.0.2
Summary: A simple calculator package
Home-page: https://github.com/halimahO/calculator.git
Author: Halimah Oladosu
Author-email: haleemaholadosu@gmail.com
License: UNKNOWN
Project-URL: Bug Tracker, https://github.com/halimahO/calculator/issues
Platform: UNKNOWN
Classifier: Programming Language :: Python :: 3
Classifier: License :: OSI Approved
Classifier: Operating System :: OS Independent
Requires-Python: >=3.6
License-File: LICENSE
